NotSoFastQC/__init__.py
NotSoFastQC/__main__.py
NotSoFastQC/fastqc_manager.py
NotSoFastQC/modules.py
NotSoFastQC/utils.py
NotSoFastQC-1.1.dist-info/LICENSE
NotSoFastQC-1.1.dist-info/METADATA
NotSoFastQC-1.1.dist-info/WHEEL
NotSoFastQC-1.1.dist-info/entry_points.txt
NotSoFastQC-1.1.dist-info/top_level.txt
NotSoFastQC-1.1.dist-info/RECORD
