Metadata-Version: 2.1
Name: NotSoFastQC
Version: 1.1
Summary: A tool to generate FastQC-like graphs from a FastQC file
Home-page: https://github.com/jamesfox96/NotSoFastQC
License: UNKNOWN
Platform: UNKNOWN
Requires-Dist: tabulate (>=0.8.7)
Requires-Dist: pandas (>=0.25.0rc0)
Requires-Dist: matplotlib (>=3.3.2)
Requires-Dist: seaborn (>=0.11.0)
Requires-Dist: numpy (>=1.17.0rc1)
Requires-Dist: scipy (>=1.5.4)
